{
"meta":{"test_sets":[],"test_metrics":[],"learn_metrics":[{"best_value":"Min","name":"RMSE"}],"launch_mode":"Train","parameters":"","iteration_count":500,"learn_sets":["learn"],"name":"experiment"},
"iterations":[
{"learn":[16.80689842],"iteration":0,"passed_time":0.09778131167,"remaining_time":48.79287453},
{"learn":[15.62187053],"iteration":1,"passed_time":0.1059630246,"remaining_time":26.38479313},
{"learn":[14.61626307],"iteration":2,"passed_time":0.1134210509,"remaining_time":18.79008743},
{"learn":[13.73663587],"iteration":3,"passed_time":0.1219037285,"remaining_time":15.11606234},
{"learn":[12.92618044],"iteration":4,"passed_time":0.1297224112,"remaining_time":12.84251871},
{"learn":[12.22959687],"iteration":5,"passed_time":0.137409775,"remaining_time":11.31340481},
{"learn":[11.64675583],"iteration":6,"passed_time":0.1450871307,"remaining_time":10.21827935},
{"learn":[11.13224305],"iteration":7,"passed_time":0.1523833903,"remaining_time":9.371578505},
{"learn":[10.74292677],"iteration":8,"passed_time":0.1593500643,"remaining_time":8.693431287},
{"learn":[10.34528264],"iteration":9,"passed_time":0.1667577133,"remaining_time":8.171127949},
{"learn":[10.01472504],"iteration":10,"passed_time":0.1738916874,"remaining_time":7.730275923},
{"learn":[9.714203586],"iteration":11,"passed_time":0.1814494221,"remaining_time":7.378943165},
{"learn":[9.46205708],"iteration":12,"passed_time":0.1886031916,"remaining_time":7.065365717},
{"learn":[9.2418623],"iteration":13,"passed_time":0.1962521682,"remaining_time":6.812753837},
{"learn":[9.056453516],"iteration":14,"passed_time":0.2033661038,"remaining_time":6.575504024},
{"learn":[8.879805613],"iteration":15,"passed_time":0.2105378797,"remaining_time":6.36877086},
{"learn":[8.729915611],"iteration":16,"passed_time":0.2179137011,"remaining_time":6.191312802},
{"learn":[8.598183389],"iteration":17,"passed_time":0.2251729401,"remaining_time":6.02963095},
{"learn":[8.495000475],"iteration":18,"passed_time":0.2321493965,"remaining_time":5.877045248},
{"learn":[8.378899306],"iteration":19,"passed_time":0.2397016046,"remaining_time":5.75283851},
{"learn":[8.256778123],"iteration":20,"passed_time":0.2468032819,"remaining_time":5.629465336},
{"learn":[8.170867737],"iteration":21,"passed_time":0.2537386299,"remaining_time":5.513048412},
{"learn":[8.092676822],"iteration":22,"passed_time":0.2609444751,"remaining_time":5.411761505},
{"learn":[8.021027407],"iteration":23,"passed_time":0.2682047191,"remaining_time":5.319393595},
{"learn":[7.956425313],"iteration":24,"passed_time":0.2754512447,"remaining_time":5.23357365},
{"learn":[7.867790075],"iteration":25,"passed_time":0.2825126493,"remaining_time":5.150422915},
{"learn":[7.788024446],"iteration":26,"passed_time":0.2898083697,"remaining_time":5.077013292},
{"learn":[7.733430109],"iteration":27,"passed_time":0.2970265523,"remaining_time":5.007019024},
{"learn":[7.66997415],"iteration":28,"passed_time":0.3040034828,"remaining_time":4.937435876},
{"learn":[7.620169005],"iteration":29,"passed_time":0.3110736817,"remaining_time":4.87348768},
{"learn":[7.567328772],"iteration":30,"passed_time":0.3183317381,"remaining_time":4.816051134},
{"learn":[7.50677994],"iteration":31,"passed_time":0.3256137484,"remaining_time":4.762101071},
{"learn":[7.464817948],"iteration":32,"passed_time":0.3324662169,"remaining_time":4.704900705},
{"learn":[7.42580926],"iteration":33,"passed_time":0.3391363483,"remaining_time":4.648162892},
{"learn":[7.3818676],"iteration":34,"passed_time":0.3467679654,"remaining_time":4.607060112},
{"learn":[7.352196653],"iteration":35,"passed_time":0.3535389479,"remaining_time":4.556724218},
{"learn":[7.323075398],"iteration":36,"passed_time":0.360315655,"remaining_time":4.508814818},
{"learn":[7.293410634],"iteration":37,"passed_time":0.367519129,"remaining_time":4.468258884},
{"learn":[7.266894824],"iteration":38,"passed_time":0.3747474022,"remaining_time":4.429706472},
{"learn":[7.245469446],"iteration":39,"passed_time":0.3817602155,"remaining_time":4.390242478},
{"learn":[7.227841236],"iteration":40,"passed_time":0.3884864206,"remaining_time":4.349152855},
{"learn":[7.188546916],"iteration":41,"passed_time":0.3957404968,"remaining_time":4.315455894},
{"learn":[7.16309566],"iteration":42,"passed_time":0.4030127021,"remaining_time":4.283181509},
{"learn":[7.142421735],"iteration":43,"passed_time":0.4103994699,"remaining_time":4.25323087},
{"learn":[7.125902717],"iteration":44,"passed_time":0.4171929343,"remaining_time":4.218284113},
{"learn":[7.099382622],"iteration":45,"passed_time":0.424292899,"remaining_time":4.187586438},
{"learn":[7.084828837],"iteration":46,"passed_time":0.4311241237,"remaining_time":4.155302724},
{"learn":[7.068915758],"iteration":47,"passed_time":0.4382956708,"remaining_time":4.127284233},
{"learn":[7.039951939],"iteration":48,"passed_time":0.4453636981,"remaining_time":4.099163834},
{"learn":[7.02759776],"iteration":49,"passed_time":0.4524824145,"remaining_time":4.072341731},
{"learn":[7.010539579],"iteration":50,"passed_time":0.4595656871,"remaining_time":4.045980265},
{"learn":[6.98497814],"iteration":51,"passed_time":0.467019889,"remaining_time":4.023555967},
{"learn":[6.973327232],"iteration":52,"passed_time":0.4740086784,"remaining_time":3.997771307},
{"learn":[6.961328817],"iteration":53,"passed_time":0.481743141,"remaining_time":3.978841498},
{"learn":[6.953057999],"iteration":54,"passed_time":0.4883237906,"remaining_time":3.950983397},
{"learn":[6.943939351],"iteration":55,"passed_time":0.4951387817,"remaining_time":3.925743197},
{"learn":[6.928827226],"iteration":56,"passed_time":0.5024087169,"remaining_time":3.904685291},
{"learn":[6.919714554],"iteration":57,"passed_time":0.5093258727,"remaining_time":3.881414409},
{"learn":[6.912377997],"iteration":58,"passed_time":0.5166941289,"remaining_time":3.862069675},
{"learn":[6.901029315],"iteration":59,"passed_time":0.5240563318,"remaining_time":3.843079767},
{"learn":[6.891636689],"iteration":60,"passed_time":0.5310011644,"remaining_time":3.821467396},
{"learn":[6.886118155],"iteration":61,"passed_time":0.5377302209,"remaining_time":3.798803819},
{"learn":[6.864215458],"iteration":62,"passed_time":0.5451451968,"remaining_time":3.781403984},
{"learn":[6.854244675],"iteration":63,"passed_time":0.552359324,"remaining_time":3.762947895},
{"learn":[6.844987256],"iteration":64,"passed_time":0.5595110384,"remaining_time":3.744420026},
{"learn":[6.835723463],"iteration":65,"passed_time":0.5664874492,"remaining_time":3.725084136},
{"learn":[6.826969146],"iteration":66,"passed_time":0.5739021659,"remaining_time":3.708949819},
{"learn":[6.820966697],"iteration":67,"passed_time":0.5805332892,"remaining_time":3.688093838},
{"learn":[6.814547053],"iteration":68,"passed_time":0.5874726417,"remaining_time":3.669575486},
{"learn":[6.808730235],"iteration":69,"passed_time":0.5944682093,"remaining_time":3.651733285},
{"learn":[6.80228692],"iteration":70,"passed_time":0.6017289851,"remaining_time":3.635799079},
{"learn":[6.792612848],"iteration":71,"passed_time":0.6085971958,"remaining_time":3.617772219},
{"learn":[6.788029484],"iteration":72,"passed_time":0.6155474928,"remaining_time":3.600531225},
{"learn":[6.784691066],"iteration":73,"passed_time":0.6223487707,"remaining_time":3.582710491},
{"learn":[6.779816383],"iteration":74,"passed_time":0.6295743632,"remaining_time":3.567588058},
{"learn":[6.775018241],"iteration":75,"passed_time":0.6365810512,"remaining_time":3.55145218},
{"learn":[6.763139585],"iteration":76,"passed_time":0.6439060772,"remaining_time":3.537302216},
{"learn":[6.759775122],"iteration":77,"passed_time":0.6506623915,"remaining_time":3.520250375},
{"learn":[6.755448508],"iteration":78,"passed_time":0.6580726162,"remaining_time":3.506943942},
{"learn":[6.748860282],"iteration":79,"passed_time":0.6653089691,"remaining_time":3.492872088},
{"learn":[6.744240466],"iteration":80,"passed_time":0.6721478656,"remaining_time":3.476913033},
{"learn":[6.734406302],"iteration":81,"passed_time":0.6796774403,"remaining_time":3.464697196},
{"learn":[6.730584886],"iteration":82,"passed_time":0.6867802039,"remaining_time":3.45044994},
{"learn":[6.727194297],"iteration":83,"passed_time":0.6938417926,"remaining_time":3.436168877},
{"learn":[6.719429046],"iteration":84,"passed_time":0.7009445079,"remaining_time":3.42225848},
{"learn":[6.717598085],"iteration":85,"passed_time":0.7082156258,"remaining_time":3.409317082},
{"learn":[6.713551888],"iteration":86,"passed_time":0.7154287272,"remaining_time":3.396230624},
{"learn":[6.710923596],"iteration":87,"passed_time":0.7221969191,"remaining_time":3.381194667},
{"learn":[6.705778258],"iteration":88,"passed_time":0.7296795557,"remaining_time":3.369643791},
{"learn":[6.70168704],"iteration":89,"passed_time":0.7365149235,"remaining_time":3.355234651},
{"learn":[6.698922722],"iteration":90,"passed_time":0.7432544024,"remaining_time":3.340560995},
{"learn":[6.691626974],"iteration":91,"passed_time":0.7504251441,"remaining_time":3.327972378},
{"learn":[6.688306429],"iteration":92,"passed_time":0.7570754858,"remaining_time":3.313222825},
{"learn":[6.683450369],"iteration":93,"passed_time":0.76419044,"remaining_time":3.300652326},
{"learn":[6.680823638],"iteration":94,"passed_time":0.7707664825,"remaining_time":3.285899215},
{"learn":[6.678095812],"iteration":95,"passed_time":0.7774705566,"remaining_time":3.271855259},
{"learn":[6.675290059],"iteration":96,"passed_time":0.7842710675,"remaining_time":3.258363301},
{"learn":[6.668777431],"iteration":97,"passed_time":0.7910642353,"remaining_time":3.244977782},
{"learn":[6.664860634],"iteration":98,"passed_time":0.7982108681,"remaining_time":3.233157152},
{"learn":[6.661742179],"iteration":99,"passed_time":0.804957571,"remaining_time":3.219830284},
{"learn":[6.658346533],"iteration":100,"passed_time":0.8117121388,"remaining_time":3.206664786},
{"learn":[6.655737445],"iteration":101,"passed_time":0.8186556372,"remaining_time":3.194362192},
{"learn":[6.652110503],"iteration":102,"passed_time":0.8254349422,"remaining_time":3.181530796},
{"learn":[6.648951064],"iteration":103,"passed_time":0.8323897173,"remaining_time":3.169483924},
{"learn":[6.64481962],"iteration":104,"passed_time":0.8393825494,"remaining_time":3.15767721},
{"learn":[6.638369056],"iteration":105,"passed_time":0.8462392381,"remaining_time":3.145455281},
{"learn":[6.637036935],"iteration":106,"passed_time":0.8528316398,"remaining_time":3.132362939},
{"learn":[6.633015794],"iteration":107,"passed_time":0.8602129917,"remaining_time":3.122254563},
{"learn":[6.629037188],"iteration":108,"passed_time":0.867373058,"remaining_time":3.111402437},
{"learn":[6.627010958],"iteration":109,"passed_time":0.87423598,"remaining_time":3.099563929},
{"learn":[6.624156875],"iteration":110,"passed_time":0.880911467,"remaining_time":3.087158204},
{"learn":[6.62116497],"iteration":111,"passed_time":0.8880393381,"remaining_time":3.076421993},
{"learn":[6.618714466],"iteration":112,"passed_time":0.895168871,"remaining_time":3.065755337},
{"learn":[6.616174111],"iteration":113,"passed_time":0.9020149064,"remaining_time":3.054190823},
{"learn":[6.613044347],"iteration":114,"passed_time":0.9093101805,"remaining_time":3.044212344},
{"learn":[6.610366091],"iteration":115,"passed_time":0.916282451,"remaining_time":3.033210872},
{"learn":[6.607497118],"iteration":116,"passed_time":0.9232605042,"remaining_time":3.022297206},
{"learn":[6.602280204],"iteration":117,"passed_time":0.9309359909,"remaining_time":3.013708038},
{"learn":[6.599824754],"iteration":118,"passed_time":0.9377792638,"remaining_time":3.002469744},
{"learn":[6.59719488],"iteration":119,"passed_time":0.9448952586,"remaining_time":2.992168319},
{"learn":[6.595068667],"iteration":120,"passed_time":0.9522594404,"remaining_time":2.982696925},
{"learn":[6.591552249],"iteration":121,"passed_time":0.959850608,"remaining_time":2.973963359},
{"learn":[6.589767266],"iteration":122,"passed_time":0.9671499969,"remaining_time":2.964354056},
{"learn":[6.586957832],"iteration":123,"passed_time":0.9744111326,"remaining_time":2.954666015},
{"learn":[6.58317463],"iteration":124,"passed_time":0.9814934483,"remaining_time":2.944480345},
{"learn":[6.581055278],"iteration":125,"passed_time":0.9882360794,"remaining_time":2.933335664},
{"learn":[6.579441502],"iteration":126,"passed_time":0.9954458788,"remaining_time":2.923632384},
{"learn":[6.577590462],"iteration":127,"passed_time":1.002406546,"remaining_time":2.913244023},
{"learn":[6.57452911],"iteration":128,"passed_time":1.009217814,"remaining_time":2.902479139},
{"learn":[6.570800169],"iteration":129,"passed_time":1.016221598,"remaining_time":2.892323011},
{"learn":[6.568607194],"iteration":130,"passed_time":1.022972547,"remaining_time":2.881502824},
{"learn":[6.564321988],"iteration":131,"passed_time":1.030179794,"remaining_time":2.872016396},
{"learn":[6.562154626],"iteration":132,"passed_time":1.036859991,"remaining_time":2.8611099},
{"learn":[6.560157427],"iteration":133,"passed_time":1.043615437,"remaining_time":2.850472015},
{"learn":[6.558680844],"iteration":134,"passed_time":1.050465062,"remaining_time":2.840146279},
{"learn":[6.555159433],"iteration":135,"passed_time":1.057522407,"remaining_time":2.830427619},
{"learn":[6.553212047],"iteration":136,"passed_time":1.064609741,"remaining_time":2.820827271},
{"learn":[6.550701716],"iteration":137,"passed_time":1.071779713,"remaining_time":2.811480117},
{"learn":[6.549322508],"iteration":138,"passed_time":1.078933554,"remaining_time":2.802122396},
{"learn":[6.545894337],"iteration":139,"passed_time":1.086187808,"remaining_time":2.793054364},
{"learn":[6.544346076],"iteration":140,"passed_time":1.09326056,"remaining_time":2.783549938},
{"learn":[6.541575563],"iteration":141,"passed_time":1.100465004,"remaining_time":2.774411771},
{"learn":[6.539041854],"iteration":142,"passed_time":1.10774027,"remaining_time":2.765477457},
{"learn":[6.537368753],"iteration":143,"passed_time":1.114633391,"remaining_time":2.75562144},
{"learn":[6.53472014],"iteration":144,"passed_time":1.122285933,"remaining_time":2.74766556},
{"learn":[6.532393173],"iteration":145,"passed_time":1.129846415,"remaining_time":2.739490622},
{"learn":[6.530984514],"iteration":146,"passed_time":1.136860789,"remaining_time":2.730012643},
{"learn":[6.529534961],"iteration":147,"passed_time":1.143948992,"remaining_time":2.72074355},
{"learn":[6.527227738],"iteration":148,"passed_time":1.150438595,"remaining_time":2.710093602},
{"learn":[6.52497761],"iteration":149,"passed_time":1.157319702,"remaining_time":2.700412639},
{"learn":[6.523001829],"iteration":150,"passed_time":1.164231981,"remaining_time":2.690840804},
{"learn":[6.521136724],"iteration":151,"passed_time":1.170920282,"remaining_time":2.680791171},
{"learn":[6.518995012],"iteration":152,"passed_time":1.177716268,"remaining_time":2.671029707},
{"learn":[6.517065818],"iteration":153,"passed_time":1.184537913,"remaining_time":2.661364403},
{"learn":[6.514846712],"iteration":154,"passed_time":1.191142138,"remaining_time":2.651251856},
{"learn":[6.512938346],"iteration":155,"passed_time":1.197879885,"remaining_time":2.64147872},
{"learn":[6.510509755],"iteration":156,"passed_time":1.204683781,"remaining_time":2.63188877},
{"learn":[6.508909886],"iteration":157,"passed_time":1.211461269,"remaining_time":2.622276923},
{"learn":[6.507719337],"iteration":158,"passed_time":1.218155964,"remaining_time":2.612523167},
{"learn":[6.506370376],"iteration":159,"passed_time":1.224946486,"remaining_time":2.603011282},
{"learn":[6.504878216],"iteration":160,"passed_time":1.231784055,"remaining_time":2.593632265},
{"learn":[6.503071506],"iteration":161,"passed_time":1.238668039,"remaining_time":2.584381465},
{"learn":[6.501860508],"iteration":162,"passed_time":1.245665604,"remaining_time":2.575394532},
{"learn":[6.500720993],"iteration":163,"passed_time":1.252604013,"remaining_time":2.566310661},
{"learn":[6.498664412],"iteration":164,"passed_time":1.259576601,"remaining_time":2.55732219},
{"learn":[6.497285526],"iteration":165,"passed_time":1.266246943,"remaining_time":2.547749874},
{"learn":[6.496175776],"iteration":166,"passed_time":1.273139033,"remaining_time":2.538654479},
{"learn":[6.494173261],"iteration":167,"passed_time":1.280564094,"remaining_time":2.530638568},
{"learn":[6.492418905],"iteration":168,"passed_time":1.287758811,"remaining_time":2.5221785},
{"learn":[6.490137998],"iteration":169,"passed_time":1.294682808,"remaining_time":2.513207803},
{"learn":[6.487203628],"iteration":170,"passed_time":1.301985344,"remaining_time":2.504989346},
{"learn":[6.485195919],"iteration":171,"passed_time":1.309241942,"remaining_time":2.496693936},
{"learn":[6.483248199],"iteration":172,"passed_time":1.316281191,"remaining_time":2.487999708},
{"learn":[6.481925337],"iteration":173,"passed_time":1.323049147,"remaining_time":2.478816219},
{"learn":[6.480074827],"iteration":174,"passed_time":1.329485826,"remaining_time":2.469045105},
{"learn":[6.478240318],"iteration":175,"passed_time":1.336899522,"remaining_time":2.461110484},
{"learn":[6.476395797],"iteration":176,"passed_time":1.344247785,"remaining_time":2.453062341},
{"learn":[6.475131781],"iteration":177,"passed_time":1.351114589,"remaining_time":2.444151111},
{"learn":[6.473609529],"iteration":178,"passed_time":1.358195482,"remaining_time":2.435646646},
{"learn":[6.471793143],"iteration":179,"passed_time":1.365303025,"remaining_time":2.427205378},
{"learn":[6.470387534],"iteration":180,"passed_time":1.372062373,"remaining_time":2.418165176},
{"learn":[6.468343464],"iteration":181,"passed_time":1.379027257,"remaining_time":2.409509163},
{"learn":[6.467386469],"iteration":182,"passed_time":1.386067814,"remaining_time":2.401002717},
{"learn":[6.466001945],"iteration":183,"passed_time":1.393022572,"remaining_time":2.392364852},
{"learn":[6.464810095],"iteration":184,"passed_time":1.399940853,"remaining_time":2.383683073},
{"learn":[6.46365505],"iteration":185,"passed_time":1.406770677,"remaining_time":2.374870927},
{"learn":[6.462695621],"iteration":186,"passed_time":1.413315915,"remaining_time":2.365603643},
{"learn":[6.461094995],"iteration":187,"passed_time":1.420646201,"remaining_time":2.357668163},
{"learn":[6.460166988],"iteration":188,"passed_time":1.427391813,"remaining_time":2.348777005},
{"learn":[6.456562093],"iteration":189,"passed_time":1.435020182,"remaining_time":2.341348718},
{"learn":[6.455523372],"iteration":190,"passed_time":1.442150602,"remaining_time":2.333112754},
{"learn":[6.453928661],"iteration":191,"passed_time":1.448983072,"remaining_time":2.324410344},
{"learn":[6.452555731],"iteration":192,"passed_time":1.455768748,"remaining_time":2.315652879},
{"learn":[6.451199626],"iteration":193,"passed_time":1.462655051,"remaining_time":2.307074463},
{"learn":[6.450033197],"iteration":194,"passed_time":1.470313861,"remaining_time":2.29972168},
{"learn":[6.448194542],"iteration":195,"passed_time":1.477687945,"remaining_time":2.29192416},
{"learn":[6.446793018],"iteration":196,"passed_time":1.484555856,"remaining_time":2.283352408},
{"learn":[6.445797573],"iteration":197,"passed_time":1.49187791,"remaining_time":2.27549055},
{"learn":[6.44473401],"iteration":198,"passed_time":1.498804012,"remaining_time":2.267035214},
{"learn":[6.443775978],"iteration":199,"passed_time":1.505603595,"remaining_time":2.258405392},
{"learn":[6.442623965],"iteration":200,"passed_time":1.51225951,"remaining_time":2.249580067},
{"learn":[6.441158917],"iteration":201,"passed_time":1.519358603,"remaining_time":2.241430018},
{"learn":[6.440116961],"iteration":202,"passed_time":1.526606989,"remaining_time":2.233508748},
{"learn":[6.437560415],"iteration":203,"passed_time":1.533612622,"remaining_time":2.225241843},
{"learn":[6.436486607],"iteration":204,"passed_time":1.540640975,"remaining_time":2.21701994},
{"learn":[6.435088747],"iteration":205,"passed_time":1.54769833,"remaining_time":2.208851014},
{"learn":[6.433515589],"iteration":206,"passed_time":1.554478839,"remaining_time":2.200300965},
{"learn":[6.432377734],"iteration":207,"passed_time":1.56144686,"remaining_time":2.192031169},
{"learn":[6.431055772],"iteration":208,"passed_time":1.568372837,"remaining_time":2.18371529},
{"learn":[6.430335092],"iteration":209,"passed_time":1.575019505,"remaining_time":2.175026935},
{"learn":[6.428288615],"iteration":210,"passed_time":1.582076033,"remaining_time":2.166919306},
{"learn":[6.426808465],"iteration":211,"passed_time":1.58956772,"remaining_time":2.159412751},
{"learn":[6.425100169],"iteration":212,"passed_time":1.596491963,"remaining_time":2.151141753},
{"learn":[6.4239238],"iteration":213,"passed_time":1.603566129,"remaining_time":2.143083705},
{"learn":[6.42292013],"iteration":214,"passed_time":1.610353415,"remaining_time":2.134654527},
{"learn":[6.421913834],"iteration":215,"passed_time":1.617560404,"remaining_time":2.126792383},
{"learn":[6.420515965],"iteration":216,"passed_time":1.624717431,"remaining_time":2.11887112},
{"learn":[6.419078908],"iteration":217,"passed_time":1.63152104,"remaining_time":2.110499694},
{"learn":[6.41823986],"iteration":218,"passed_time":1.638254172,"remaining_time":2.102052157},
{"learn":[6.4165959],"iteration":219,"passed_time":1.64548004,"remaining_time":2.094247323},
{"learn":[6.415445214],"iteration":220,"passed_time":1.652575872,"remaining_time":2.086283567},
{"learn":[6.414493172],"iteration":221,"passed_time":1.659527885,"remaining_time":2.078147531},
{"learn":[6.413855936],"iteration":222,"passed_time":1.665985789,"remaining_time":2.069408356},
{"learn":[6.412765949],"iteration":223,"passed_time":1.672789029,"remaining_time":2.061115053},
{"learn":[6.411525421],"iteration":224,"passed_time":1.679625216,"remaining_time":2.052875264},
{"learn":[6.410342112],"iteration":225,"passed_time":1.68685317,"remaining_time":2.04512287},
{"learn":[6.409136618],"iteration":226,"passed_time":1.694097616,"remaining_time":2.03739493},
{"learn":[6.4069703],"iteration":227,"passed_time":1.701461101,"remaining_time":2.029813243},
{"learn":[6.405770537],"iteration":228,"passed_time":1.708442256,"remaining_time":2.021781011},
{"learn":[6.403924709],"iteration":229,"passed_time":1.715563944,"remaining_time":2.013922891},
{"learn":[6.403189212],"iteration":230,"passed_time":1.7223056,"remaining_time":2.0056286},
{"learn":[6.402086417],"iteration":231,"passed_time":1.729111023,"remaining_time":1.997421355},
{"learn":[6.400892969],"iteration":232,"passed_time":1.736035191,"remaining_time":1.989362214},
{"learn":[6.399763779],"iteration":233,"passed_time":1.743066762,"remaining_time":1.981434866},
{"learn":[6.398480369],"iteration":234,"passed_time":1.750592171,"remaining_time":1.974072023},
{"learn":[6.397404623],"iteration":235,"passed_time":1.757426858,"remaining_time":1.965935129},
{"learn":[6.395925126],"iteration":236,"passed_time":1.7645957,"remaining_time":1.958180038},
{"learn":[6.394247521],"iteration":237,"passed_time":1.771689864,"remaining_time":1.950347665},
{"learn":[6.393031922],"iteration":238,"passed_time":1.778842876,"remaining_time":1.942585735},
{"learn":[6.392145679],"iteration":239,"passed_time":1.785958605,"remaining_time":1.934788488},
{"learn":[6.391354238],"iteration":240,"passed_time":1.792509135,"remaining_time":1.926389485},
{"learn":[6.390025173],"iteration":241,"passed_time":1.79988773,"remaining_time":1.918888571},
{"learn":[6.388986262],"iteration":242,"passed_time":1.806711882,"remaining_time":1.910802279},
{"learn":[6.388058484],"iteration":243,"passed_time":1.813791498,"remaining_time":1.902994359},
{"learn":[6.386942409],"iteration":244,"passed_time":1.820948566,"remaining_time":1.895272997},
{"learn":[6.385496528],"iteration":245,"passed_time":1.828404754,"remaining_time":1.887865071},
{"learn":[6.384296181],"iteration":246,"passed_time":1.835027822,"remaining_time":1.879603397},
{"learn":[6.383309742],"iteration":247,"passed_time":1.842119602,"remaining_time":1.871831209},
{"learn":[6.382419264],"iteration":248,"passed_time":1.849188825,"remaining_time":1.864041748},
{"learn":[6.381480758],"iteration":249,"passed_time":1.856627036,"remaining_time":1.856627036},
{"learn":[6.380526711],"iteration":250,"passed_time":1.86352853,"remaining_time":1.848679697},
{"learn":[6.37985956],"iteration":251,"passed_time":1.870390118,"remaining_time":1.840701386},
{"learn":[6.378816067],"iteration":252,"passed_time":1.877156721,"remaining_time":1.83263917},
{"learn":[6.377517614],"iteration":253,"passed_time":1.883978261,"remaining_time":1.824640363},
{"learn":[6.376713199],"iteration":254,"passed_time":1.890841558,"remaining_time":1.816690908},
{"learn":[6.376151786],"iteration":255,"passed_time":1.897563391,"remaining_time":1.808615107},
{"learn":[6.375223536],"iteration":256,"passed_time":1.904349669,"remaining_time":1.800610777},
{"learn":[6.374313649],"iteration":257,"passed_time":1.911455561,"remaining_time":1.792915681},
{"learn":[6.373190422],"iteration":258,"passed_time":1.918459531,"remaining_time":1.785130297},
{"learn":[6.372325003],"iteration":259,"passed_time":1.925539462,"remaining_time":1.777421042},
{"learn":[6.371657154],"iteration":260,"passed_time":1.932759316,"remaining_time":1.769844738},
{"learn":[6.37015343],"iteration":261,"passed_time":1.939370834,"remaining_time":1.761718544},
{"learn":[6.369207663],"iteration":262,"passed_time":1.94603687,"remaining_time":1.753652997},
{"learn":[6.368273439],"iteration":263,"passed_time":1.953048371,"remaining_time":1.745906877},
{"learn":[6.366003274],"iteration":264,"passed_time":1.960843164,"remaining_time":1.738860919},
{"learn":[6.364782843],"iteration":265,"passed_time":1.968104155,"remaining_time":1.731339745},
{"learn":[6.363808291],"iteration":266,"passed_time":1.975248547,"remaining_time":1.723718769},
{"learn":[6.362960013],"iteration":267,"passed_time":1.98248141,"remaining_time":1.716177937},
{"learn":[6.362085694],"iteration":268,"passed_time":1.989463133,"remaining_time":1.708423732},
{"learn":[6.361076977],"iteration":269,"passed_time":1.996539177,"remaining_time":1.700755596},
{"learn":[6.35978295],"iteration":270,"passed_time":2.003195476,"remaining_time":1.692737137},
{"learn":[6.358801446],"iteration":271,"passed_time":2.010533894,"remaining_time":1.68530047},
{"learn":[6.357953146],"iteration":272,"passed_time":2.017014082,"remaining_time":1.677150903},
{"learn":[6.357111622],"iteration":273,"passed_time":2.024175847,"remaining_time":1.669575699},
{"learn":[6.356095029],"iteration":274,"passed_time":2.031352112,"remaining_time":1.662015364},
{"learn":[6.355096903],"iteration":275,"passed_time":2.0383787,"remaining_time":1.654336336},
{"learn":[6.354582445],"iteration":276,"passed_time":2.045332492,"remaining_time":1.646603414},
{"learn":[6.353794322],"iteration":277,"passed_time":2.052019064,"remaining_time":1.638662706},
{"learn":[6.353007287],"iteration":278,"passed_time":2.058601474,"remaining_time":1.630648479},
{"learn":[6.35216787],"iteration":279,"passed_time":2.065418569,"remaining_time":1.622828875},
{"learn":[6.351207856],"iteration":280,"passed_time":2.07290532,"remaining_time":1.61553831},
{"learn":[6.350376763],"iteration":281,"passed_time":2.080280418,"remaining_time":1.608160039},
{"learn":[6.349468985],"iteration":282,"passed_time":2.087833854,"remaining_time":1.600918538},
{"learn":[6.348885354],"iteration":283,"passed_time":2.09477698,"remaining_time":1.593210661},
{"learn":[6.348159566],"iteration":284,"passed_time":2.101929522,"remaining_time":1.585666131},
{"learn":[6.347198401],"iteration":285,"passed_time":2.109204254,"remaining_time":1.578215771},
{"learn":[6.346213322],"iteration":286,"passed_time":2.11601011,"remaining_time":1.570418653},
{"learn":[6.345112183],"iteration":287,"passed_time":2.122981533,"remaining_time":1.562750295},
{"learn":[6.34402137],"iteration":288,"passed_time":2.129659658,"remaining_time":1.554872622},
{"learn":[6.342595538],"iteration":289,"passed_time":2.136697527,"remaining_time":1.547263726},
{"learn":[6.340843856],"iteration":290,"passed_time":2.143760934,"remaining_time":1.539677097},
{"learn":[6.340105242],"iteration":291,"passed_time":2.150745029,"remaining_time":1.532037555},
{"learn":[6.33884776],"iteration":292,"passed_time":2.158281309,"remaining_time":1.524792597},
{"learn":[6.33772379],"iteration":293,"passed_time":2.165725831,"remaining_time":1.517481364},
{"learn":[6.336662518],"iteration":294,"passed_time":2.172559692,"remaining_time":1.509744871},
{"learn":[6.335724344],"iteration":295,"passed_time":2.179123927,"remaining_time":1.501828653},
{"learn":[6.333920129],"iteration":296,"passed_time":2.186184311,"remaining_time":1.494260657},
{"learn":[6.332898914],"iteration":297,"passed_time":2.19337664,"remaining_time":1.486785508},
{"learn":[6.331888534],"iteration":298,"passed_time":2.200384211,"remaining_time":1.479188048},
{"learn":[6.331255739],"iteration":299,"passed_time":2.20713759,"remaining_time":1.47142506},
{"learn":[6.330155359],"iteration":300,"passed_time":2.214129789,"remaining_time":1.463826671},
{"learn":[6.329292506],"iteration":301,"passed_time":2.221225058,"remaining_time":1.456299873},
{"learn":[6.328591584],"iteration":302,"passed_time":2.228101533,"remaining_time":1.44863367},
{"learn":[6.327732785],"iteration":303,"passed_time":2.23520167,"remaining_time":1.441116866},
{"learn":[6.326761083],"iteration":304,"passed_time":2.242435905,"remaining_time":1.43368853},
{"learn":[6.32599793],"iteration":305,"passed_time":2.24922612,"remaining_time":1.425979958},
{"learn":[6.324601752],"iteration":306,"passed_time":2.256791624,"remaining_time":1.418764767},
{"learn":[6.323933038],"iteration":307,"passed_time":2.263673868,"remaining_time":1.411121372},
{"learn":[6.323186413],"iteration":308,"passed_time":2.270613951,"remaining_time":1.403518656},
{"learn":[6.322269178],"iteration":309,"passed_time":2.277709971,"remaining_time":1.396015789},
{"learn":[6.321055534],"iteration":310,"passed_time":2.285071667,"remaining_time":1.388676994},
{"learn":[6.320375801],"iteration":311,"passed_time":2.291936094,"remaining_time":1.381038416},
{"learn":[6.319583566],"iteration":312,"passed_time":2.298909312,"remaining_time":1.373469781},
{"learn":[6.318339768],"iteration":313,"passed_time":2.306264141,"remaining_time":1.366130988},
{"learn":[6.317552337],"iteration":314,"passed_time":2.312791982,"remaining_time":1.358306402},
{"learn":[6.316820498],"iteration":315,"passed_time":2.3196465,"remaining_time":1.35068024},
{"learn":[6.315699199],"iteration":316,"passed_time":2.326390195,"remaining_time":1.342994971},
{"learn":[6.314788608],"iteration":317,"passed_time":2.333514782,"remaining_time":1.335533617},
{"learn":[6.313766465],"iteration":318,"passed_time":2.340257995,"remaining_time":1.327857985},
{"learn":[6.312545254],"iteration":319,"passed_time":2.347282022,"remaining_time":1.320346137},
{"learn":[6.31162874],"iteration":320,"passed_time":2.354269736,"remaining_time":1.31281708},
{"learn":[6.310776066],"iteration":321,"passed_time":2.361281911,"remaining_time":1.305304907},
{"learn":[6.310053714],"iteration":322,"passed_time":2.368128085,"remaining_time":1.297704864},
{"learn":[6.309078772],"iteration":323,"passed_time":2.375041867,"remaining_time":1.290146199},
{"learn":[6.307937421],"iteration":324,"passed_time":2.382345365,"remaining_time":1.28280135},
{"learn":[6.307101739],"iteration":325,"passed_time":2.389680791,"remaining_time":1.275473797},
{"learn":[6.30640972],"iteration":326,"passed_time":2.396553642,"remaining_time":1.267901468},
{"learn":[6.305664198],"iteration":327,"passed_time":2.403666421,"remaining_time":1.260459221},
{"learn":[6.304196063],"iteration":328,"passed_time":2.4113646,"remaining_time":1.253323242},
{"learn":[6.30348347],"iteration":329,"passed_time":2.41839241,"remaining_time":1.245838514},
{"learn":[6.302679753],"iteration":330,"passed_time":2.425521401,"remaining_time":1.238408208},
{"learn":[6.301703754],"iteration":331,"passed_time":2.432939075,"remaining_time":1.231125797},
{"learn":[6.301105778],"iteration":332,"passed_time":2.439672095,"remaining_time":1.223499219},
{"learn":[6.300209456],"iteration":333,"passed_time":2.446217995,"remaining_time":1.215784992},
{"learn":[6.299224159],"iteration":334,"passed_time":2.452911117,"remaining_time":1.208150252},
{"learn":[6.298298756],"iteration":335,"passed_time":2.459936448,"remaining_time":1.200683266},
{"learn":[6.296841607],"iteration":336,"passed_time":2.467490256,"remaining_time":1.193474516},
{"learn":[6.296452555],"iteration":337,"passed_time":2.474856709,"remaining_time":1.186173926},
{"learn":[6.295845959],"iteration":338,"passed_time":2.483076995,"remaining_time":1.179278455},
{"learn":[6.294471842],"iteration":339,"passed_time":2.491145344,"remaining_time":1.172303691},
{"learn":[6.29362711],"iteration":340,"passed_time":2.499253621,"remaining_time":1.165341131},
{"learn":[6.292733851],"iteration":341,"passed_time":2.507575736,"remaining_time":1.158470662},
{"learn":[6.2922313],"iteration":342,"passed_time":2.515521121,"remaining_time":1.151419289},
{"learn":[6.290957126],"iteration":343,"passed_time":2.52309446,"remaining_time":1.144193999},
{"learn":[6.290072553],"iteration":344,"passed_time":2.532117944,"remaining_time":1.137618207},
{"learn":[6.289309319],"iteration":345,"passed_time":2.540800208,"remaining_time":1.130876393},
{"learn":[6.288454345],"iteration":346,"passed_time":2.549884743,"remaining_time":1.124300765},
{"learn":[6.287596994],"iteration":347,"passed_time":2.55888186,"remaining_time":1.117672536},
{"learn":[6.286832099],"iteration":348,"passed_time":2.566558842,"remaining_time":1.110459556},
{"learn":[6.28533425],"iteration":349,"passed_time":2.575031159,"remaining_time":1.103584782},
{"learn":[6.284824629],"iteration":350,"passed_time":2.583481692,"remaining_time":1.096691659},
{"learn":[6.283453045],"iteration":351,"passed_time":2.592661928,"remaining_time":1.090096492},
{"learn":[6.28261577],"iteration":352,"passed_time":2.601669133,"remaining_time":1.083414625},
{"learn":[6.281853289],"iteration":353,"passed_time":2.609411824,"remaining_time":1.076198097},
{"learn":[6.280976153],"iteration":354,"passed_time":2.618497979,"remaining_time":1.069527343},
{"learn":[6.280324886],"iteration":355,"passed_time":2.627020155,"remaining_time":1.062614894},
{"learn":[6.279365365],"iteration":356,"passed_time":2.635378894,"remaining_time":1.05562796},
{"learn":[6.27846369],"iteration":357,"passed_time":2.64323973,"remaining_time":1.048435871},
{"learn":[6.277279346],"iteration":358,"passed_time":2.652125227,"remaining_time":1.041642498},
{"learn":[6.276535158],"iteration":359,"passed_time":2.660960048,"remaining_time":1.034817797},
{"learn":[6.275826179],"iteration":360,"passed_time":2.669353115,"remaining_time":1.027811864},
{"learn":[6.274766241],"iteration":361,"passed_time":2.677743925,"remaining_time":1.020797408},
{"learn":[6.2739277],"iteration":362,"passed_time":2.686552183,"remaining_time":1.013932918},
{"learn":[6.273334269],"iteration":363,"passed_time":2.694579974,"remaining_time":1.006766144},
{"learn":[6.271994312],"iteration":364,"passed_time":2.702687337,"remaining_time":0.9996240834},
{"learn":[6.271248802],"iteration":365,"passed_time":2.710705252,"remaining_time":0.9924439992},
{"learn":[6.2703795],"iteration":366,"passed_time":2.718471214,"remaining_time":0.9851680423},
{"learn":[6.269474284],"iteration":367,"passed_time":2.726312615,"remaining_time":0.9779164813},
{"learn":[6.26863016],"iteration":368,"passed_time":2.733902391,"remaining_time":0.9705723936},
{"learn":[6.267947356],"iteration":369,"passed_time":2.741068877,"remaining_time":0.963078254},
{"learn":[6.267346095],"iteration":370,"passed_time":2.748345423,"remaining_time":0.9556241496},
{"learn":[6.266338297],"iteration":371,"passed_time":2.755938974,"remaining_time":0.9482800769},
{"learn":[6.26583838],"iteration":372,"passed_time":2.763479346,"remaining_time":0.9409165602},
{"learn":[6.265263759],"iteration":373,"passed_time":2.770626216,"remaining_time":0.9334195272},
{"learn":[6.264185197],"iteration":374,"passed_time":2.777780632,"remaining_time":0.9259268772},
{"learn":[6.263502989],"iteration":375,"passed_time":2.785305527,"remaining_time":0.9185582058},
{"learn":[6.262869636],"iteration":376,"passed_time":2.79228999,"remaining_time":0.911012384},
{"learn":[6.262174267],"iteration":377,"passed_time":2.799745762,"remaining_time":0.903621648},
{"learn":[6.261431194],"iteration":378,"passed_time":2.806995357,"remaining_time":0.8961647446},
{"learn":[6.260591394],"iteration":379,"passed_time":2.81400321,"remaining_time":0.8886325925},
{"learn":[6.25992242],"iteration":380,"passed_time":2.821166976,"remaining_time":0.8811518903},
{"learn":[6.259209265],"iteration":381,"passed_time":2.828400847,"remaining_time":0.8736945023},
{"learn":[6.258500255],"iteration":382,"passed_time":2.835411179,"remaining_time":0.8661699946},
{"learn":[6.257103221],"iteration":383,"passed_time":2.842930771,"remaining_time":0.8588020039},
{"learn":[6.256379473],"iteration":384,"passed_time":2.849797009,"remaining_time":0.8512380677},
{"learn":[6.255905061],"iteration":385,"passed_time":2.856763391,"remaining_time":0.8437073227},
{"learn":[6.255307842],"iteration":386,"passed_time":2.86362885,"remaining_time":0.8361500261},
{"learn":[6.254332778],"iteration":387,"passed_time":2.871232029,"remaining_time":0.8288092454},
{"learn":[6.253942477],"iteration":388,"passed_time":2.878203205,"remaining_time":0.8212867758},
{"learn":[6.253412902],"iteration":389,"passed_time":2.885459944,"remaining_time":0.8138476764},
{"learn":[6.252649906],"iteration":390,"passed_time":2.892523149,"remaining_time":0.8063555583},
{"learn":[6.251916073],"iteration":391,"passed_time":2.899568055,"remaining_time":0.7988605866},
{"learn":[6.251070306],"iteration":392,"passed_time":2.906481614,"remaining_time":0.7913321443},
{"learn":[6.25053731],"iteration":393,"passed_time":2.913390664,"remaining_time":0.7838056102},
{"learn":[6.249873369],"iteration":394,"passed_time":2.920495589,"remaining_time":0.7763342705},
{"learn":[6.249270114],"iteration":395,"passed_time":2.927492502,"remaining_time":0.7688364146},
{"learn":[6.248574041],"iteration":396,"passed_time":2.934265805,"remaining_time":0.7612830677},
{"learn":[6.248104882],"iteration":397,"passed_time":2.940788988,"remaining_time":0.7536695396},
{"learn":[6.247154728],"iteration":398,"passed_time":2.947687904,"remaining_time":0.7461565873},
{"learn":[6.24620075],"iteration":399,"passed_time":2.954610444,"remaining_time":0.7386526111},
{"learn":[6.24537244],"iteration":400,"passed_time":2.961564213,"remaining_time":0.7311592446},
{"learn":[6.244645582],"iteration":401,"passed_time":2.968107039,"remaining_time":0.7235683826},
{"learn":[6.243996038],"iteration":402,"passed_time":2.974709124,"remaining_time":0.7159969851},
{"learn":[6.24328522],"iteration":403,"passed_time":2.981903491,"remaining_time":0.7085711266},
{"learn":[6.242704667],"iteration":404,"passed_time":2.988549116,"remaining_time":0.701017694},
{"learn":[6.242237287],"iteration":405,"passed_time":2.995081824,"remaining_time":0.6934425899},
{"learn":[6.241617287],"iteration":406,"passed_time":3.001844533,"remaining_time":0.6859251635},
{"learn":[6.240863178],"iteration":407,"passed_time":3.009228528,"remaining_time":0.6785515309},
{"learn":[6.239955748],"iteration":408,"passed_time":3.01654127,"remaining_time":0.6711619942},
{"learn":[6.239229145],"iteration":409,"passed_time":3.023881427,"remaining_time":0.6637788497},
{"learn":[6.238771975],"iteration":410,"passed_time":3.030699033,"remaining_time":0.6562827589},
{"learn":[6.237964618],"iteration":411,"passed_time":3.037488567,"remaining_time":0.6487839659},
{"learn":[6.237180232],"iteration":412,"passed_time":3.044312916,"remaining_time":0.6412959411},
{"learn":[6.236156775],"iteration":413,"passed_time":3.051475591,"remaining_time":0.633881403},
{"learn":[6.235430995],"iteration":414,"passed_time":3.058603171,"remaining_time":0.6264608904},
{"learn":[6.234353087],"iteration":415,"passed_time":3.065722965,"remaining_time":0.6190402141},
{"learn":[6.233764892],"iteration":416,"passed_time":3.072425126,"remaining_time":0.6115378549},
{"learn":[6.232989709],"iteration":417,"passed_time":3.079532378,"remaining_time":0.6041187918},
{"learn":[6.232093914],"iteration":418,"passed_time":3.086767219,"remaining_time":0.5967258825},
{"learn":[6.231483569],"iteration":419,"passed_time":3.093745294,"remaining_time":0.5892848179},
{"learn":[6.231151817],"iteration":420,"passed_time":3.100776593,"remaining_time":0.5818559403},
{"learn":[6.230704443],"iteration":421,"passed_time":3.107528841,"remaining_time":0.5743773687},
{"learn":[6.230233496],"iteration":422,"passed_time":3.114063832,"remaining_time":0.5668626834},
{"learn":[6.229705687],"iteration":423,"passed_time":3.120504177,"remaining_time":0.5593356544},
{"learn":[6.228965461],"iteration":424,"passed_time":3.127722127,"remaining_time":0.5519509635},
{"learn":[6.22836373],"iteration":425,"passed_time":3.134877613,"remaining_time":0.544556205},
{"learn":[6.227831526],"iteration":426,"passed_time":3.142397517,"remaining_time":0.5372248682},
{"learn":[6.227197159],"iteration":427,"passed_time":3.149263105,"remaining_time":0.5297825784},
{"learn":[6.226645379],"iteration":428,"passed_time":3.156197684,"remaining_time":0.5223543953},
{"learn":[6.2258208],"iteration":429,"passed_time":3.16313094,"remaining_time":0.5149282925},
{"learn":[6.22480749],"iteration":430,"passed_time":3.171065669,"remaining_time":0.5076648055},
{"learn":[6.223914901],"iteration":431,"passed_time":3.177930901,"remaining_time":0.5002298641},
{"learn":[6.223314632],"iteration":432,"passed_time":3.185065686,"remaining_time":0.4928392632},
{"learn":[6.222911816],"iteration":433,"passed_time":3.192017509,"remaining_time":0.4854220175},
{"learn":[6.222274583],"iteration":434,"passed_time":3.199192726,"remaining_time":0.4780402925},
{"learn":[6.221131199],"iteration":435,"passed_time":3.206682338,"remaining_time":0.4707056643},
{"learn":[6.220736151],"iteration":436,"passed_time":3.213178299,"remaining_time":0.4632270774},
{"learn":[6.219862846],"iteration":437,"passed_time":3.220334772,"remaining_time":0.4558464746},
{"learn":[6.219182251],"iteration":438,"passed_time":3.22668046,"remaining_time":0.4483542324},
{"learn":[6.21842284],"iteration":439,"passed_time":3.233588968,"remaining_time":0.4409439501},
{"learn":[6.217682734],"iteration":440,"passed_time":3.240286561,"remaining_time":0.4335077258},
{"learn":[6.217039444],"iteration":441,"passed_time":3.246963148,"remaining_time":0.4260720873},
{"learn":[6.216382429],"iteration":442,"passed_time":3.254276665,"remaining_time":0.4187218282},
{"learn":[6.215430238],"iteration":443,"passed_time":3.261135307,"remaining_time":0.4113143631},
{"learn":[6.214630336],"iteration":444,"passed_time":3.268521307,"remaining_time":0.4039745436},
{"learn":[6.213954793],"iteration":445,"passed_time":3.275275175,"remaining_time":0.3965579809},
{"learn":[6.213198537],"iteration":446,"passed_time":3.282399699,"remaining_time":0.3891883312},
{"learn":[6.212845245],"iteration":447,"passed_time":3.289407338,"remaining_time":0.3818062088},
{"learn":[6.212141936],"iteration":448,"passed_time":3.296796461,"remaining_time":0.3744690858},
{"learn":[6.211470018],"iteration":449,"passed_time":3.303590702,"remaining_time":0.3670656336},
{"learn":[6.210682759],"iteration":450,"passed_time":3.310471659,"remaining_time":0.3596743044},
{"learn":[6.209698161],"iteration":451,"passed_time":3.317644177,"remaining_time":0.3523161958},
{"learn":[6.209354851],"iteration":452,"passed_time":3.324274286,"remaining_time":0.3449026301},
{"learn":[6.208750275],"iteration":453,"passed_time":3.33131656,"remaining_time":0.337534277},
{"learn":[6.207957207],"iteration":454,"passed_time":3.338859514,"remaining_time":0.330216875},
{"learn":[6.207360008],"iteration":455,"passed_time":3.345659546,"remaining_time":0.3228267983},
{"learn":[6.206382147],"iteration":456,"passed_time":3.352675051,"remaining_time":0.3154595781},
{"learn":[6.205448049],"iteration":457,"passed_time":3.3601945,"remaining_time":0.308140107},
{"learn":[6.204533952],"iteration":458,"passed_time":3.367776174,"remaining_time":0.3008253227},
{"learn":[6.204067928],"iteration":459,"passed_time":3.374458006,"remaining_time":0.293431131},
{"learn":[6.203444145],"iteration":460,"passed_time":3.38139864,"remaining_time":0.286061924},
{"learn":[6.202826243],"iteration":461,"passed_time":3.388371165,"remaining_time":0.2786971954},
{"learn":[6.20210951],"iteration":462,"passed_time":3.395516989,"remaining_time":0.2713480099},
{"learn":[6.201391134],"iteration":463,"passed_time":3.402554274,"remaining_time":0.2639912799},
{"learn":[6.200905543],"iteration":464,"passed_time":3.409519653,"remaining_time":0.2566305115},
{"learn":[6.200237929],"iteration":465,"passed_time":3.416535088,"remaining_time":0.2492750923},
{"learn":[6.199692595],"iteration":466,"passed_time":3.423426446,"remaining_time":0.2419123613},
{"learn":[6.198960913],"iteration":467,"passed_time":3.430169117,"remaining_time":0.2345414781},
{"learn":[6.19797117],"iteration":468,"passed_time":3.437371584,"remaining_time":0.2272036654},
{"learn":[6.197323118],"iteration":469,"passed_time":3.44437205,"remaining_time":0.2198535351},
{"learn":[6.196098226],"iteration":470,"passed_time":3.451680283,"remaining_time":0.2125238391},
{"learn":[6.195081383],"iteration":471,"passed_time":3.4586625,"remaining_time":0.2051748941},
{"learn":[6.194687045],"iteration":472,"passed_time":3.465286245,"remaining_time":0.1978070372},
{"learn":[6.193536669],"iteration":473,"passed_time":3.472329754,"remaining_time":0.1904653451},
{"learn":[6.192675842],"iteration":474,"passed_time":3.479157759,"remaining_time":0.1831135663},
{"learn":[6.191809246],"iteration":475,"passed_time":3.485828314,"remaining_time":0.1757560494},
{"learn":[6.191368571],"iteration":476,"passed_time":3.492530901,"remaining_time":0.1684029575},
{"learn":[6.190631832],"iteration":477,"passed_time":3.499439202,"remaining_time":0.1610620553},
{"learn":[6.189507327],"iteration":478,"passed_time":3.506657151,"remaining_time":0.1537365348},
{"learn":[6.188754836],"iteration":479,"passed_time":3.51409515,"remaining_time":0.1464206313},
{"learn":[6.187882071],"iteration":480,"passed_time":3.521033513,"remaining_time":0.1390844839},
{"learn":[6.187216635],"iteration":481,"passed_time":3.527871405,"remaining_time":0.131746235},
{"learn":[6.186656748],"iteration":482,"passed_time":3.534942165,"remaining_time":0.1244182543},
{"learn":[6.186313833],"iteration":483,"passed_time":3.541593634,"remaining_time":0.1170774755},
{"learn":[6.185518887],"iteration":484,"passed_time":3.548316507,"remaining_time":0.1097417476},
{"learn":[6.184708355],"iteration":485,"passed_time":3.555269584,"remaining_time":0.1024151732},
{"learn":[6.183986876],"iteration":486,"passed_time":3.562369506,"remaining_time":0.09509405251},
{"learn":[6.183542323],"iteration":487,"passed_time":3.569110216,"remaining_time":0.08776500531},
{"learn":[6.182522967],"iteration":488,"passed_time":3.576510299,"remaining_time":0.08045319691},
{"learn":[6.181823812],"iteration":489,"passed_time":3.583411008,"remaining_time":0.07313083689},
{"learn":[6.181074142],"iteration":490,"passed_time":3.590424841,"remaining_time":0.06581226796},
{"learn":[6.179925769],"iteration":491,"passed_time":3.597516075,"remaining_time":0.05849619634},
{"learn":[6.179242066],"iteration":492,"passed_time":3.604696638,"remaining_time":0.05118230521},
{"learn":[6.178636151],"iteration":493,"passed_time":3.611599024,"remaining_time":0.04386557519},
{"learn":[6.178073533],"iteration":494,"passed_time":3.618239434,"remaining_time":0.03654787307},
{"learn":[6.177221746],"iteration":495,"passed_time":3.625298265,"remaining_time":0.02923627633},
{"learn":[6.176727293],"iteration":496,"passed_time":3.632133698,"remaining_time":0.02192434828},
{"learn":[6.176271089],"iteration":497,"passed_time":3.639054051,"remaining_time":0.01461467491},
{"learn":[6.17534656],"iteration":498,"passed_time":3.646046024,"remaining_time":0.007306705458},
{"learn":[6.174775045],"iteration":499,"passed_time":3.65342061,"remaining_time":0}
]}